picammodapipkg/__init__.py
picammodapipkg/adc.py
picammodapipkg/cam.py
picammodapipkg/camproject.py
picammodapipkg/cli.py
picammodapipkg/motionDetect.py
picammodapipkg/motion_detector.py
picammodapipkg/picammodapipkg.py
picammodapipkg/takeImg.py
picammodapipkg/takeVid.py
picammodapipkg-0.1.0.dist-info/AUTHORS.rst
picammodapipkg-0.1.0.dist-info/LICENSE
picammodapipkg-0.1.0.dist-info/METADATA
picammodapipkg-0.1.0.dist-info/WHEEL
picammodapipkg-0.1.0.dist-info/entry_points.txt
picammodapipkg-0.1.0.dist-info/top_level.txt
picammodapipkg-0.1.0.dist-info/RECORD
